{"time_created": "2017-03-16 21:04:30", "user": {"image_url": "https://s3-media4.fl.yelpcdn.com/photo/W3SQdNfStfksxh3I-qhFLg/o.jpg", "name": "Alice L."}, "rating": 2, "restaurant_id": "boku-sushi-toronto", "url": "https://www.yelp.com/biz/boku-sushi-toronto?hrid=MV3atb5NksBvaRsLW2M8BQ&adjust_creative=92p07_JjKyriZTQxAXRiKQ&utm_campaign=yelp_api_v3&utm_medium=api_v3_business_reviews&utm_source=92p07_JjKyriZTQxAXRiKQ", "text": "I came here for the regular menu on a Friday night. Made reservations ahead of time but when we arrived, the place was only half occupied. \n\nWe ordered Uni..."}