{"text": "Friends recommended this place and I looked up the reviews on Yelp and pictures...food looked great! So I tried it! We ordered several appetizers: pot...", "url": "https://www.yelp.com/biz/coopers-hawk-winery-and-restaurants-tampa?hrid=h1sr24faG2h_r5KDDnw6xg&adjust_creative=92p07_JjKyriZTQxAXRiKQ&utm_campaign=yelp_api_v3&utm_medium=api_v3_business_reviews&utm_source=92p07_JjKyriZTQxAXRiKQ", "user": {"image_url": "https://s3-media1.fl.yelpcdn.com/photo/NhbVWhDCJBW6DwKhLCqi8A/o.jpg", "name": "Annie B."}, "restaurant_id": "coopers-hawk-winery-and-restaurants-tampa", "rating": 4, "time_created": "2017-01-08 18:04:04"}