{"term": "attractions", "image_url": "https://s3-media2.fl.yelpcdn.com/bphoto/xtJDN-qh5miql2nNBS0Obw/o.jpg", "hours": [{"hours_type": "REGULAR", "is_open_now": false, "open": [{"start": "0700", "is_overnight": false, "end": "0000", "day": 0}, {"start": "0700", "is_overnight": false, "end": "0000", "day": 1}, {"start": "0700", "is_overnight": false, "end": "0000", "day": 2}, {"start": "0700", "is_overnight": false, "end": "0000", "day": 3}, {"start": "0700", "is_overnight": false, "end": "0000", "day": 4}, {"start": "0700", "is_overnight": false, "end": "0000", "day": 5}, {"start": "0700", "is_overnight": false, "end": "0000", "day": 6}]}], "categories": [{"alias": "beaches", "title": "Beaches"}, {"alias": "localflavor", "title": "Local Flavor"}], "is_claimed": false, "rating": 3.5, "phone": "", "url": "https://www.yelp.com/biz/paris-plages-paris-2?adjust_creative=92p07_JjKyriZTQxAXRiKQ&utm_campaign=yelp_api_v3&utm_medium=api_v3_business_lookup&utm_source=92p07_JjKyriZTQxAXRiKQ", "price": "\u20ac", "is_closed": false, "review_count": 28, "location": {"country": "FR", "zip_code": "75019", "city": "Paris", "state": "75", "address1": "Voie Georges Pompidou", "address2": "", "address3": ""}, "name": "Paris Plages", "coordinates": {"longitude": 2.3655, "latitude": 48.84654}, "id": "paris-plages-paris-2", "photos": ["https://s3-media3.fl.yelpcdn.com/bphoto/xtJDN-qh5miql2nNBS0Obw/o.jpg", "https://s3-media2.fl.yelpcdn.com/bphoto/nYTPvi2zxk1EzxDn2aUy6Q/o.jpg", "https://s3-media2.fl.yelpcdn.com/bphoto/9uQmbWBBN7jtcU3jhvB_1w/o.jpg"]}