{"blog": [], "keywords": [{"value": "Global Warming", "name": "subject", "rank": "1", "is_major": "N"}, {"value": "Obama, Barack", "name": "persons", "rank": "2", "is_major": "N"}], "web_url": "http://www.nytimes.com/2015/05/25/opinion/mitigating-climate-change.html", "document_type": "article", "byline": [], "type_of_material": "Letter", "multimedia": [], "section_name": "Opinion", "word_count": "171", "source": "The New York Times", "subsection_name": null, "lead_paragraph": "A reader encourages states to support President Obama&#8217;s initiative through their own environmental actions.", "pub_date": "2015-05-25T00:00:00Z", "news_desk": "Letters", "headline": {"kicker": "Letter", "print_headline": "Mitigating Climate Change", "main": "Mitigating Climate Change", "content_kicker": "Letter"}, "print_page": "18", "snippet": "A reader encourages states to support President Obama&#8217;s initiative through their own environmental actions.", "_id": "5562cd6638f0d82dd9493559", "slideshow_credits": null, "abstract": null}