{"blog": [], "keywords": [{"value": "Editorials", "name": "subject", "rank": "1", "is_major": "Y"}, {"value": "Smuggling", "name": "subject", "rank": "11", "is_major": "N"}, {"value": "Human Rights and Human Rights Violations", "name": "subject", "rank": "12", "is_major": "N"}, {"value": "Human Trafficking", "name": "subject", "rank": "13", "is_major": "Y"}, {"value": "Rohingya (Ethnic Group)", "name": "subject", "rank": "2", "is_major": "Y"}, {"value": "Myanmar", "name": "glocations", "rank": "3", "is_major": "Y"}, {"value": "Far East, South and Southeast Asia and Pacific Areas", "name": "glocations", "rank": "4", "is_major": "Y"}, {"value": "Refugees and Displaced Persons", "name": "subject", "rank": "5", "is_major": "Y"}, {"value": "Bangladesh", "name": "glocations", "rank": "6", "is_major": "N"}, {"value": "Malaysia", "name": "glocations", "rank": "7", "is_major": "N"}, {"value": "Thailand", "name": "glocations", "rank": "8", "is_major": "N"}, {"value": "Indonesia", "name": "glocations", "rank": "9", "is_major": "N"}, {"value": "Illegal Immigration", "name": "subject", "rank": "10", "is_major": "N"}], "web_url": "http://www.nytimes.com/2015/05/29/opinion/horrors-of-human-trafficking-in-south-asia.html", "document_type": "article", "byline": {"person": [], "original": "By THE EDITORIAL BOARD", "organization": "THE EDITORIAL BOARD"}, "type_of_material": "Editorial", "multimedia": [{"url": "images/2015/05/29/opinion/29fri2Web/29fri2Web-thumbWide.jpg", "legacy": {"wide": "images/2015/05/29/opinion/29fri2Web/29fri2Web-thumbWide.jpg", "wideheight": "126", "widewidth": "190"}, "subtype": "wide", "type": "image", "width": 190, "height": 126}, {"url": "images/2015/05/29/opinion/29fri2Web/29fri2Web-articleLarge.jpg", "legacy": {"xlarge": "images/2015/05/29/opinion/29fri2Web/29fri2Web-articleLarge.jpg", "xlargeheight": "400", "xlargewidth": "600"}, "subtype": "xlarge", "type": "image", "width": 600, "height": 400}, {"url": "images/2015/05/29/opinion/29fri2Web/29fri2Web-thumbStandard.jpg", "legacy": {"thumbnail": "images/2015/05/29/opinion/29fri2Web/29fri2Web-thumbStandard.jpg", "thumbnailheight": "75", "thumbnailwidth": "75"}, "subtype": "thumbnail", "type": "image", "width": 75, "height": 75}], "section_name": "Opinion", "word_count": "559", "source": "The New York Times", "subsection_name": null, "lead_paragraph": "Governments in the region must take responsibility for the crisis they have created.", "pub_date": "2015-05-29T00:00:00Z", "news_desk": "Editorial", "headline": {"kicker": "Editorial", "print_headline": "Horrors of Human Trafficking", "main": "Horrors of Human Trafficking in South Asia", "content_kicker": "Editorial"}, "print_page": "22", "snippet": "Governments in the region must take responsibility for the crisis they have created.", "_id": "5568137638f0d8572a7b75de", "slideshow_credits": null, "abstract": "Editorial calls on South Asian governments of Bangladesh, Thailand, Indonesia, Malaysia and particularly Myanmar to alter policies that have led to rampant human trafficking in region, forcing thousands of migrants to take to sea to find refuge; calls government of Myanmar one of worst offenders, with systematic persecution of Rohingya Muslims driving 140,000 from their homes and making them highly vulnerable to traffickers."}