{"blog": [], "keywords": [{"value": "Florida", "name": "glocations", "rank": "1", "is_major": "N"}, {"value": "Louisiana", "name": "glocations", "rank": "2", "is_major": "N"}, {"value": "Weather", "name": "subject", "rank": "3", "is_major": "N"}, {"value": "Tornadoes", "name": "subject", "rank": "4", "is_major": "N"}, {"value": "Pensacola (Fla)", "name": "glocations", "rank": "5", "is_major": "N"}], "web_url": "http://www.nytimes.com/video/us/100000004230557/storms-batter-the-south.html", "document_type": "multimedia", "byline": [], "type_of_material": "Video", "multimedia": [{"url": "images/2016/02/24/multimedia/25storms-south/25storms-south-thumbWide.jpg", "legacy": {"wide": "images/2016/02/24/multimedia/25storms-south/25storms-south-thumbWide.jpg", "wideheight": "126", "widewidth": "190"}, "subtype": "wide", "type": "image", "width": 190, "height": 126}, {"url": "images/2016/02/24/multimedia/25storms-south/25storms-south-articleLarge.jpg", "legacy": {"xlarge": "images/2016/02/24/multimedia/25storms-south/25storms-south-articleLarge.jpg", "xlargeheight": "338", "xlargewidth": "600"}, "subtype": "xlarge", "type": "image", "width": 600, "height": 338}, {"url": "images/2016/02/24/multimedia/25storms-south/25storms-south-thumbStandard.jpg", "legacy": {"thumbnail": "images/2016/02/24/multimedia/25storms-south/25storms-south-thumbStandard.jpg", "thumbnailheight": "75", "thumbnailwidth": "75"}, "subtype": "thumbnail", "type": "image", "width": 75, "height": 75}], "section_name": "U.S.", "word_count": "36", "source": "The New York Times", "subsection_name": null, "lead_paragraph": "Gov. Rick Scott of Florida spoke in the aftermath of a severe weather system that tore through the South, spurring tornadoes in his state and in Louisiana. Storms continued to threaten the East Coast on Wednesday.", "pub_date": "2016-02-24T13:13:58Z", "news_desk": "U.S.", "headline": {"main": "Storms Batter the South"}, "print_page": null, "snippet": "Gov. Rick Scott of Florida spoke in the aftermath of a severe weather system that tore through the South, spurring tornadoes in his state and in Louisiana. Storms continued to threaten the East Coast on Wednesday.", "_id": "56cdf2fa38f0d8622592d3cd", "slideshow_credits": null, "abstract": null}