{"blog": [], "keywords": [{"value": "Golf", "name": "subject", "rank": "1", "is_major": "Y"}, {"value": "Hoffman, Charley", "name": "persons", "rank": "2", "is_major": "Y"}, {"value": "Reed, Patrick", "name": "persons", "rank": "3", "is_major": "N"}, {"value": "Texas Open (Golf)", "name": "subject", "rank": "4", "is_major": "N"}], "web_url": "http://www.nytimes.com/2016/04/25/sports/tennis/charley-hoffman-wins-on-final-hole-at-texas-open.html", "document_type": "article", "byline": {"person": [], "original": "By THE ASSOCIATED PRESS", "contributor": "", "organization": "THE ASSOCIATED PRESS"}, "type_of_material": "Brief", "multimedia": [], "section_name": "Sports", "word_count": "180", "source": "The New York Times", "subsection_name": "Tennis", "lead_paragraph": "Hoffman made a 9-foot birdie putt on the final hole to win the Valero Texas Open. Hoffman closed with a three-under 69 at TPC San Antonio.", "pub_date": "2016-04-25T00:00:00Z", "news_desk": "Sports", "headline": {"print_headline": "Hoffman Wins on Final Hole", "main": "Charley Hoffman Wins on Final Hole at Texas Open", "content_kicker": "Sports Briefing | Golf"}, "print_page": "4", "snippet": "Hoffman made a 9-foot birdie putt on the final hole to win the Valero Texas Open. Hoffman closed with a three-under 69 at TPC San Antonio.", "_id": "571d969b38f0d8550bf1a763", "slideshow_credits": null, "abstract": "Charley Hoffman wins Valero Texas Open, marking his fourth PGA Tour victory; other golf news noted."}