{"blog": [], "keywords": [{"value": "SUTTER, MEYER", "name": "persons"}], "web_url": "http://query.nytimes.com/gst/fullpage.html?res=9800E7DE123AF932A15757C0A9609D8B63", "document_type": "article", "byline": null, "type_of_material": "Paid Death Notice", "multimedia": [], "section_name": "Paid Death Notices", "word_count": "14", "source": "The New York Times", "subsection_name": null, "lead_paragraph": "SUTTER--Meyer. April 21, 1997. Dear father, always loved and remembered. Larry and Betty 1/3", "pub_date": "2016-04-21T00:00:00Z", "news_desk": "Classified", "headline": {"main": "Paid Notice: Memorials  SUTTER, MEYER"}, "print_page": "27", "snippet": "SUTTER--Meyer. April 21, 1997. Dear father, always loved and remembered. Larry and Betty 1/3", "_id": "5722cf0b38f0d83c40473c92", "slideshow_credits": null, "abstract": null}