{"blog": [], "keywords": [{"value": "Marques'Almeida (Fashion Label)", "name": "organizations", "rank": "1", "is_major": "N"}, {"value": "London Fashion Week", "name": "subject", "rank": "3", "is_major": "N"}], "web_url": "http://www.nytimes.com/slideshow/2016/09/20/fashion/runway-womens/marquesalmeida-spring-2017.html", "document_type": "multimedia", "byline": [], "type_of_material": "Slideshow", "multimedia": [{"url": "images/2016/09/20/fashion/runway-womens/malmeida-slide-Z3YR/malmeida-slide-Z3YR-thumbWide.jpg", "legacy": {"wide": "images/2016/09/20/fashion/runway-womens/malmeida-slide-Z3YR/malmeida-slide-Z3YR-thumbWide.jpg", "wideheight": "126", "widewidth": "190"}, "subtype": "wide", "type": "image", "width": 190, "height": 126}, {"url": "images/2016/09/20/fashion/runway-womens/malmeida-slide-Z3YR/malmeida-slide-Z3YR-articleLarge.jpg", "legacy": {"xlarge": "images/2016/09/20/fashion/runway-womens/malmeida-slide-Z3YR/malmeida-slide-Z3YR-articleLarge.jpg", "xlargeheight": "900", "xlargewidth": "600"}, "subtype": "xlarge", "type": "image", "width": 600, "height": 900}, {"url": "images/2016/09/20/fashion/runway-womens/malmeida-slide-Z3YR/malmeida-slide-Z3YR-thumbStandard.jpg", "legacy": {"thumbnail": "images/2016/09/20/fashion/runway-womens/malmeida-slide-Z3YR/malmeida-slide-Z3YR-thumbStandard.jpg", "thumbnailheight": "75", "thumbnailwidth": "75"}, "subtype": "thumbnail", "type": "image", "width": 75, "height": 75}], "section_name": "Fashion & Style", "word_count": "20", "source": "The New York Times", "subsection_name": "Women's Runway", "lead_paragraph": "Marta Marques and Paulo Almeida, who are experimenting with sending ads as personalized emails to fans, show their spring collection.", "pub_date": "2016-09-20T04:00:00+0000", "news_desk": "Fashion & Style / Women's Runway", "headline": {"kicker": "Spring 2017", "main": "Marques\u2019Almeida: Spring 2017"}, "print_page": null, "snippet": "Marta Marques and Paulo Almeida, who are experimenting with sending ads as personalized emails to fans, show their spring collection....", "_id": "57e13ff195d0e021d798748e", "slideshow_credits": "Gio Staiano/Nowfashion", "abstract": null}