{"web_url": "http://www.nytimes.com/reuters/2014/10/07/business/07reuters-buffett-investing-fortune.html", "multimedia": [], "subsection_name": null, "print_page": null, "blog": [], "section_name": "Business Day", "abstract": null, "type_of_material": "News", "lead_paragraph": "Billionaire investor Warren Buffett on Tuesday predicted Democrat Hillary Clinton would run for the U.S. presidency in 2016 and win.", "keywords": [], "_id": "5434257938f0d86add490c9b", "pub_date": "2014-10-07T13:39:41Z", "byline": {"organization": "REUTERS", "original": "By REUTERS", "person": []}, "news_desk": "None", "slideshow_credits": null, "word_count": "280", "source": "Reuters", "headline": {"main": "Berkshire's Buffett Predicts Hillary Clinton Will Win Presidency in 2016", "print_headline": "Berkshire's Buffett Predicts Hillary Clinton Will Win Presidency in 2016"}, "snippet": "Billionaire investor Warren Buffett on Tuesday predicted Democrat Hillary Clinton would run for the U.S. presidency in 2016 and win....", "document_type": "article"}