{"web_url": "http://www.nytimes.com/interactive/2015/09/24/us/politics/document.html", "multimedia": [{"legacy": {"wideheight": "126", "wide": "images/2015/09/24/us/politics/document-1443144582895/document-1443144582895-thumbWide.png", "widewidth": "190"}, "type": "image", "subtype": "wide", "height": 126, "width": 190, "url": "images/2015/09/24/us/politics/document-1443144582895/document-1443144582895-thumbWide.png"}, {"legacy": {"thumbnailheight": "75", "thumbnail": "images/2015/09/24/us/politics/document-1443144582895/document-1443144582895-thumbStandard.png", "thumbnailwidth": "75"}, "type": "image", "subtype": "thumbnail", "height": 75, "width": 75, "url": "images/2015/09/24/us/politics/document-1443144582895/document-1443144582895-thumbStandard.png"}], "subsection_name": "Politics", "print_page": null, "blog": [], "section_name": "U.S.", "abstract": null, "type_of_material": "Interactive Feature", "lead_paragraph": "The document, part of a process by which Huma Abedin, an aide to Hillary Rodham Clinton, became a special government employee at the State Department, describes Ms. Abedin\u2019s new title as \u201csenior advisor.\u201d", "keywords": [{"value": "Government Employees", "name": "subject", "rank": "1", "is_major": "N"}, {"value": "State Department", "name": "organizations", "rank": "2", "is_major": "N"}, {"value": "Abedin, Huma", "name": "persons", "rank": "3", "is_major": "N"}, {"value": "Clinton, Hillary Rodham", "name": "persons", "rank": "4", "is_major": "N"}, {"value": "Presidential Election of 2016", "name": "subject", "rank": "5", "is_major": "N"}], "_id": "5604aa7438f0d86906c7b750", "pub_date": "2015-09-24T00:00:00Z", "byline": [], "news_desk": "U.S. / Politics", "slideshow_credits": null, "word_count": null, "source": "The New York Times", "headline": {"main": "Document Signed by Hillary Clinton in 2012 Regarding Huma Abedin\u2019s New Job"}, "snippet": "The document, part of a process by which Huma Abedin, an aide to Hillary Rodham Clinton, became a special government employee at the State Department, describes Ms. Abedin\u2019s new title as \u201csenior advisor.\u201d...", "document_type": "multimedia"}