{"time_created": "2017-03-24 10:50:49", "url": "https://www.yelp.com/biz/5411-empanadas-houston-2?hrid=F1oqThFMrMhsU2ssg6fr6w&adjust_creative=92p07_JjKyriZTQxAXRiKQ&utm_campaign=yelp_api_v3&utm_medium=api_v3_business_reviews&utm_source=92p07_JjKyriZTQxAXRiKQ", "restaurant_id": "5411-empanadas-houston-2", "user": {"name": "Andrew L.", "image_url": "https://s3-media2.fl.yelpcdn.com/photo/Ybhu4CaKXWwoZkCFlpDEvA/o.jpg"}, "text": "This place is awesome! Usually quite a line when I'm walking through the tunnels for lunch, so I end up deciding to go somewhere else. On this day, I walked...", "rating": 5}