{"text": "It's OMG good!! I had such a long day, both physically and mentally. BUT! BrightWok help me get my soul my power back!! Super delicious!! \n\nAfter finishing...", "url": "https://www.yelp.com/biz/brightwok-kitchen-chicago?hrid=In5lbNyXFdXXAlznCVUBKA&adjust_creative=92p07_JjKyriZTQxAXRiKQ&utm_campaign=yelp_api_v3&utm_medium=api_v3_business_reviews&utm_source=92p07_JjKyriZTQxAXRiKQ", "time_created": "2017-04-19 13:38:59", "user": {"name": "Kun L.", "image_url": "https://s3-media3.fl.yelpcdn.com/photo/pVZPgz-9hMDxvHS60-MQnw/o.jpg"}, "rating": 5, "restaurant_id": "brightwok-kitchen-chicago"}