{"text": "What a great eclectic flare on a burger and sandwich joint...creative recipes and great good.  \n\nMy wife and I wanted to try something new and came across...", "url": "https://www.yelp.com/biz/doc-bs-fresh-kitchen-tampa?hrid=bR7a-EH17aAemLC-zsCmbg&adjust_creative=92p07_JjKyriZTQxAXRiKQ&utm_campaign=yelp_api_v3&utm_medium=api_v3_business_reviews&utm_source=92p07_JjKyriZTQxAXRiKQ", "user": {"image_url": "https://s3-media4.fl.yelpcdn.com/photo/_Cgee7pfIELHwyEdMFbnIA/o.jpg", "name": "Anthony M."}, "restaurant_id": "doc-bs-fresh-kitchen-tampa", "rating": 5, "time_created": "2017-04-16 14:27:02"}