{"coordinates": {"latitude": 42.6431041472751, "longitude": -71.3069599811469}, "image_url": "https://s3-media4.fl.yelpcdn.com/bphoto/IVE3dPJOQ7jKb6ELYJuZpw/o.jpg", "url": "https://www.yelp.com/biz/cafe-utec-lowell?adjust_creative=92p07_JjKyriZTQxAXRiKQ&utm_campaign=yelp_api_v3&utm_medium=api_v3_business_lookup&utm_source=92p07_JjKyriZTQxAXRiKQ", "review_count": 19, "photos": ["https://s3-media2.fl.yelpcdn.com/bphoto/IVE3dPJOQ7jKb6ELYJuZpw/o.jpg", "https://s3-media1.fl.yelpcdn.com/bphoto/Yj5JxkJethD5G7Hwgg5o7Q/o.jpg", "https://s3-media4.fl.yelpcdn.com/bphoto/gtazttHeNykczTENu7A5ew/o.jpg"], "price": "$", "phone": "+19788563974", "rating": 5.0, "hours": [{"is_open_now": false, "hours_type": "REGULAR", "open": [{"start": "1100", "end": "1500", "day": 0, "is_overnight": false}, {"start": "1100", "end": "1500", "day": 1, "is_overnight": false}, {"start": "1100", "end": "1500", "day": 2, "is_overnight": false}, {"start": "1100", "end": "1500", "day": 3, "is_overnight": false}]}], "term": "restaurants", "is_closed": false, "id": "cafe-utec-lowell", "display_phone": "(978) 856-3974", "categories": [{"title": "Cafes", "alias": "cafes"}, {"title": "Sandwiches", "alias": "sandwiches"}, {"title": "Salad", "alias": "salad"}], "transactions": [], "location": {"country": "US", "address2": null, "state": "MA", "zip_code": "01852", "address3": "", "address1": "41 Warren St", "city": "Lowell", "display_address": ["41 Warren St", "Lowell, MA 01852"], "cross_streets": ""}, "name": "Cafe UTEC", "is_claimed": true}