{"text": "I was told this was one of the best restaurants in Melbourne and I was honestly a bit disappointed. I arrived on a Wednesday evening and the place was...", "url": "https://www.yelp.com/biz/cumulus-melbourne-2?hrid=mhL9coq8XYMb4QXFny_Wsg&adjust_creative=92p07_JjKyriZTQxAXRiKQ&utm_campaign=yelp_api_v3&utm_medium=api_v3_business_reviews&utm_source=92p07_JjKyriZTQxAXRiKQ", "user": {"image_url": "https://s3-media3.fl.yelpcdn.com/photo/mGTzE7E-PqZFpC0yy3suSg/o.jpg", "name": "Shannon W."}, "restaurant_id": "cumulus-melbourne-2", "rating": 3, "time_created": "2017-02-13 23:45:01"}