{"time_created": "2017-03-26 12:47:51", "url": "https://www.yelp.com/biz/piattini-boston-3?hrid=6RqDJEKyhMa70j5mtHUpnQ&adjust_creative=92p07_JjKyriZTQxAXRiKQ&utm_campaign=yelp_api_v3&utm_medium=api_v3_business_reviews&utm_source=92p07_JjKyriZTQxAXRiKQ", "restaurant_id": "piattini-boston-3", "user": {"name": "Lauren E.", "image_url": "https://s3-media3.fl.yelpcdn.com/photo/GCYcImXNgBHRLLn_GezJLA/o.jpg"}, "text": "Such a great spot! The waitress was awesome, gave great recommendations and explained the wine pairing menu to us when we told her we had never been here...", "rating": 5}