{"time_created": "2017-04-10 17:09:47", "user": {"image_url": "https://s3-media4.fl.yelpcdn.com/photo/DV7VlOt241lGrEJBNDcUvA/o.jpg", "name": "Karen N."}, "rating": 4, "restaurant_id": "george-toronto", "url": "https://www.yelp.com/biz/george-toronto?hrid=t86rWU7FHHwM-SluYQ-klQ&adjust_creative=92p07_JjKyriZTQxAXRiKQ&utm_campaign=yelp_api_v3&utm_medium=api_v3_business_reviews&utm_source=92p07_JjKyriZTQxAXRiKQ", "text": "For my 100th Yelp review, I'm reviewing George restaurant!\n\nWe went here for Valentine's Day. My co-worker Maurits recommended this place to me after having..."}