{"time_created": "2016-11-21 15:17:13", "user": {"image_url": "https://s3-media2.fl.yelpcdn.com/photo/6mqKrBDm8Pz4owROM3Nd0w/o.jpg", "name": "Philipp P."}, "rating": 5, "restaurant_id": "primus-hotel-sydney-sydney", "url": "https://www.yelp.com/biz/primus-hotel-sydney-sydney?hrid=6Koc8KEDFRRfgdHW26P4Hw&adjust_creative=92p07_JjKyriZTQxAXRiKQ&utm_campaign=yelp_api_v3&utm_medium=api_v3_business_reviews&utm_source=92p07_JjKyriZTQxAXRiKQ", "text": "I had an absolutely excellent stay at the Primus Hotel. It's beautifully designed with lots of concrete walls and rich colors, space is not a compromise at..."}