{"time_created": "2017-04-17 09:07:21", "user": {"image_url": "https://s3-media4.fl.yelpcdn.com/photo/xdfQWPoLjP-vmGQ1-5VQFA/o.jpg", "name": "Gloria K."}, "rating": 4, "restaurant_id": "beast-toronto", "url": "https://www.yelp.com/biz/beast-toronto?hrid=yDaDZHrGJCClRn7hp49oiA&adjust_creative=92p07_JjKyriZTQxAXRiKQ&utm_campaign=yelp_api_v3&utm_medium=api_v3_business_reviews&utm_source=92p07_JjKyriZTQxAXRiKQ", "text": "During my stay in Toronto, me and a couple friends went to try Canadian food. Since I'm Korean, every time I see kimchi anywhere on the menu, that's usually..."}