{"text": "Friendly hostess and servers, but the meal was disappointing. We arrived a few minutes early for our reservation and had a short wait but, I didn't mind. We...", "url": "https://www.yelp.com/biz/knife-and-tine-chicago-2?hrid=YjuM3QzHVlA6TcvNLARfvw&adjust_creative=92p07_JjKyriZTQxAXRiKQ&utm_campaign=yelp_api_v3&utm_medium=api_v3_business_reviews&utm_source=92p07_JjKyriZTQxAXRiKQ", "time_created": "2017-04-13 17:26:10", "user": {"name": "Christopher V.", "image_url": "https://s3-media3.fl.yelpcdn.com/photo/KxcmuN402UShsdp4aygzVg/o.jpg"}, "rating": 3, "restaurant_id": "knife-and-tine-chicago-2"}