{"text": "Delicious and so filling. Went with the 3 scoops of salmon on a bed of mixed salad and brown rice. Unlike other poke places, this place lets you load up on...", "url": "https://www.yelp.com/biz/pokiology-chicago?hrid=d_F2_Cn_xQk1KArVNrEL2Q&adjust_creative=92p07_JjKyriZTQxAXRiKQ&utm_campaign=yelp_api_v3&utm_medium=api_v3_business_reviews&utm_source=92p07_JjKyriZTQxAXRiKQ", "time_created": "2017-04-03 09:51:45", "user": {"name": "Maria A.", "image_url": "https://s3-media2.fl.yelpcdn.com/photo/PVC6sIw_MwlBp9QcOObOXw/o.jpg"}, "rating": 5, "restaurant_id": "pokiology-chicago"}