{"text": "Excellent and very satisfying food. We had the Wagyu cheeseburger dumplings to start and we shared the following: lamb shoulders with steamed buns and beef...", "url": "https://www.yelp.com/biz/burma-lane-melbourne?hrid=tVzkxAjAQv9YEi-s3BrAXA&adjust_creative=92p07_JjKyriZTQxAXRiKQ&utm_campaign=yelp_api_v3&utm_medium=api_v3_business_reviews&utm_source=92p07_JjKyriZTQxAXRiKQ", "user": {"image_url": "https://s3-media2.fl.yelpcdn.com/photo/ct4AzjSz1vs-xm_2rRaG9w/o.jpg", "name": "Chad B."}, "restaurant_id": "burma-lane-melbourne", "rating": 5, "time_created": "2017-03-11 02:16:14"}