{"text": "This place was good but not as good as the hype.  Service was very slow and although the waiter was extremely friendly, he was having a hard time keeping...", "url": "https://www.yelp.com/biz/the-morrison-los-angeles?hrid=Q93F4L-U_26HAyhOuf6Vng&adjust_creative=92p07_JjKyriZTQxAXRiKQ&utm_campaign=yelp_api_v3&utm_medium=api_v3_business_reviews&utm_source=92p07_JjKyriZTQxAXRiKQ", "user": {"image_url": "https://s3-media3.fl.yelpcdn.com/photo/aIGe7QWI2I2Qge9WFy1gIw/o.jpg", "name": "James G."}, "restaurant_id": "the-morrison-los-angeles", "rating": 3, "time_created": "2017-04-10 19:29:00"}