{"time_created": "2017-02-25 19:13:02", "user": {"image_url": "https://s3-media4.fl.yelpcdn.com/photo/HkMUcK458cX-SdWtEDkRSA/o.jpg", "name": "Dave L."}, "rating": 1, "restaurant_id": "mellow-mushroom-wellington", "url": "https://www.yelp.com/biz/mellow-mushroom-wellington?hrid=WfJ1yXnH71HREUxHxvWVpw&adjust_creative=92p07_JjKyriZTQxAXRiKQ&utm_campaign=yelp_api_v3&utm_medium=api_v3_business_reviews&utm_source=92p07_JjKyriZTQxAXRiKQ", "text": "First time eating here, my kids said it was awful but agreed to try it again. It was still awful. Waiter and staff were great, cool atmosphere, very clean,..."}