{"text": "As matter of fact, was there last night for Valentines Day with hubby.  It was the first time I've been there since new construction.  When you enter there...", "url": "https://www.yelp.com/biz/cozys-cottage-liberty-township?hrid=K-xwhXVHvz8sMZJK2J3GgQ&adjust_creative=92p07_JjKyriZTQxAXRiKQ&utm_campaign=yelp_api_v3&utm_medium=api_v3_business_reviews&utm_source=92p07_JjKyriZTQxAXRiKQ", "user": {"image_url": "https://s3-media2.fl.yelpcdn.com/photo/37YAZyvBqdwBc696H2Rq_A/o.jpg", "name": "Maryann H."}, "restaurant_id": "cozys-cottage-liberty-township", "rating": 5, "time_created": "2017-02-15 12:11:10"}