{"image_url": "https://s3-media1.fl.yelpcdn.com/bphoto/vjjE90A28GWCjg31h0fG5A/o.jpg", "phone": "+16175621668", "categories": [{"alias": "taiwanese", "title": "Taiwanese"}, {"alias": "bubbletea", "title": "Bubble Tea"}], "name": "Dolphin Bay", "hours": [{"is_open_now": false, "hours_type": "REGULAR", "open": [{"is_overnight": false, "end": "2200", "day": 0, "start": "1100"}, {"is_overnight": false, "end": "2200", "day": 1, "start": "1100"}, {"is_overnight": false, "end": "2200", "day": 2, "start": "1100"}, {"is_overnight": false, "end": "2200", "day": 3, "start": "1100"}, {"is_overnight": false, "end": "2200", "day": 4, "start": "1100"}, {"is_overnight": false, "end": "2200", "day": 5, "start": "1100"}, {"is_overnight": false, "end": "2200", "day": 6, "start": "1100"}]}], "transactions": [], "is_claimed": true, "term": "restaurants", "photos": ["https://s3-media3.fl.yelpcdn.com/bphoto/vjjE90A28GWCjg31h0fG5A/o.jpg", "https://s3-media3.fl.yelpcdn.com/bphoto/V-YEw6Cc29KIdZzEfywe8Q/o.jpg", "https://s3-media4.fl.yelpcdn.com/bphoto/9GwjHqb0ewsRnqcnQe0zFQ/o.jpg"], "review_count": 239, "id": "dolphin-bay-boston", "is_closed": false, "url": "https://www.yelp.com/biz/dolphin-bay-boston?adjust_creative=92p07_JjKyriZTQxAXRiKQ&utm_campaign=yelp_api_v3&utm_medium=api_v3_business_lookup&utm_source=92p07_JjKyriZTQxAXRiKQ", "coordinates": {"latitude": 42.3524595116339, "longitude": -71.128802412403}, "price": "$", "location": {"country": "US", "cross_streets": "Chester St & Reedsdale St", "display_address": ["72 Brighton Ave", "Boston, MA 02134"], "address1": "72 Brighton Ave", "zip_code": "02134", "address3": "", "address2": "", "state": "MA", "city": "Boston"}, "rating": 4.5, "display_phone": "(617) 562-1668"}