{"time_created": "2017-03-26 16:57:01", "user": {"image_url": "https://s3-media4.fl.yelpcdn.com/photo/iIcXtHgMdbyGSVmEpcw2cw/o.jpg", "name": "Paulina G."}, "rating": 5, "restaurant_id": "angolino-toronto", "url": "https://www.yelp.com/biz/angolino-toronto?hrid=0z6d8V_bhLP_fU1rqI5otg&adjust_creative=92p07_JjKyriZTQxAXRiKQ&utm_campaign=yelp_api_v3&utm_medium=api_v3_business_reviews&utm_source=92p07_JjKyriZTQxAXRiKQ", "text": "Amazing and cozy little resto tucked away in one of the nooks of the Junction! I called in advance to reserve for a party of 8 for a Saturday night. The..."}