{"text": "Hidden gem in Seattle! We heard about this place through a few locals when we were shopping around near the Starbucks Reserve earlier that day. What an...", "url": "https://www.yelp.com/biz/the-pink-door-seattle-4?hrid=pRQQsAC4w_-vVpGMdv_8yA&adjust_creative=92p07_JjKyriZTQxAXRiKQ&utm_campaign=yelp_api_v3&utm_medium=api_v3_business_reviews&utm_source=92p07_JjKyriZTQxAXRiKQ", "user": {"image_url": "https://s3-media2.fl.yelpcdn.com/photo/XdQMS0UN--eqB6tzmkOjLg/o.jpg", "name": "Cynthia H."}, "restaurant_id": "the-pink-door-seattle-4", "rating": 5, "time_created": "2017-03-07 14:04:20"}