{"restaurant": {"apikey": "d8c8fdcd1f3889c1d199340258ad5cc6", "events_url": "https://www.zomato.com/arirang-joondalup/events#tabtop?utm_source=api_basic_user&utm_medium=api&utm_campaign=v2.1", "deeplink": "zomato://restaurant/18357317", "R": {"res_id": 18357317}, "average_cost_for_two": 20, "is_delivering_now": 0, "user_rating": {"rating_color": "CBCBC8", "aggregate_rating": "0", "rating_text": "Not rated", "votes": "1"}, "name": "Arirang Korean Cuisine", "switch_to_order_menu": 0, "url": "https://www.zomato.com/arirang-joondalup?utm_source=api_basic_user&utm_medium=api&utm_campaign=v2.1", "menu_url": "https://www.zomato.com/arirang-joondalup/menu?utm_source=api_basic_user&utm_medium=api&utm_campaign=v2.1&openSwipeBox=menu&showMinimal=1#tabtop", "price_range": 1, "currency": "$", "photos_url": "https://www.zomato.com/arirang-joondalup/photos?utm_source=api_basic_user&utm_medium=api&utm_campaign=v2.1#tabtop", "cuisines": "Korean", "establishment_types": [], "location": {"zipcode": "6027", "city_id": 296, "country_id": 14, "longitude": "115.7709759715", "locality_verbose": "Joondalup Drive, Joondalup, Perth, WA", "locality": "Joondalup Drive, Joondalup", "country_name": "Australia", "city": "Perth", "latitude": "-31.7525192158", "address": "270 Joondalup Drive, Perth, Joondalup, Perth, WA"}, "offers": [], "id": "18357317", "thumb": "https://b.zmtcdn.com/data/pictures/7/18357317/982d23ef99fb3d4ffe0797d69e168c48_featured_v2.jpg", "has_online_delivery": 0, "featured_image": "https://b.zmtcdn.com/data/pictures/7/18357317/982d23ef99fb3d4ffe0797d69e168c48_featured_v2.jpg", "has_table_booking": 0}}