{"term": "restaurants", "image_url": "https://s3-media3.fl.yelpcdn.com/bphoto/97TCzeh2gvJSiiz1H9uK-Q/o.jpg", "hours": [{"hours_type": "REGULAR", "is_open_now": true, "open": [{"start": "1100", "is_overnight": false, "day": 0, "end": "2130"}, {"start": "1100", "is_overnight": false, "day": 1, "end": "2130"}, {"start": "1100", "is_overnight": false, "day": 2, "end": "2130"}, {"start": "1100", "is_overnight": false, "day": 3, "end": "2130"}, {"start": "1100", "is_overnight": false, "day": 4, "end": "2230"}, {"start": "1100", "is_overnight": false, "day": 5, "end": "2230"}, {"start": "1030", "is_overnight": false, "day": 6, "end": "2100"}]}], "categories": [{"alias": "breakfast_brunch", "title": "Breakfast & Brunch"}, {"alias": "gastropubs", "title": "Gastropubs"}, {"alias": "vegetarian", "title": "Vegetarian"}], "is_claimed": true, "rating": 3.5, "phone": "+17135265460", "url": "https://www.yelp.com/biz/hobbit-cafe-houston?adjust_creative=92p07_JjKyriZTQxAXRiKQ&utm_campaign=yelp_api_v3&utm_medium=api_v3_business_lookup&utm_source=92p07_JjKyriZTQxAXRiKQ", "price": "$$", "review_count": 736, "coordinates": {"longitude": -95.4140505, "latitude": 29.7340113}, "is_closed": false, "location": {"country": "US", "state": "TX", "city": "Houston", "address1": "2243 Richmond Ave", "zip_code": "77098", "address3": "", "address2": ""}, "name": "Hobbit Cafe", "id": "hobbit-cafe-houston", "photos": ["https://s3-media3.fl.yelpcdn.com/bphoto/97TCzeh2gvJSiiz1H9uK-Q/o.jpg", "https://s3-media2.fl.yelpcdn.com/bphoto/AjlWHKf2ymVUiq64cyA20w/o.jpg", "https://s3-media4.fl.yelpcdn.com/bphoto/Q60dQnmrn3RZ4BQwJinytg/o.jpg"]}