{"term": "restaurants", "image_url": "https://s3-media2.fl.yelpcdn.com/bphoto/38Czt3mQdiH2Hy7xYn96RA/o.jpg", "categories": [{"alias": "tradamerican", "title": "American (Traditional)"}], "is_claimed": true, "rating": 4.5, "phone": "+17134854720", "url": "https://www.yelp.com/biz/muscle-maker-grill-houston-5?adjust_creative=92p07_JjKyriZTQxAXRiKQ&utm_campaign=yelp_api_v3&utm_medium=api_v3_business_lookup&utm_source=92p07_JjKyriZTQxAXRiKQ", "price": "$", "review_count": 5, "coordinates": {"longitude": -95.3646249760574, "latitude": 29.7576608417512}, "is_closed": false, "location": {"country": "US", "zip_code": "77002", "city": "Houston", "state": "TX", "address1": "914 Main St", "address2": "Ste C", "address3": ""}, "name": "Muscle Maker Grill", "id": "muscle-maker-grill-houston-5", "photos": ["https://s3-media1.fl.yelpcdn.com/bphoto/38Czt3mQdiH2Hy7xYn96RA/o.jpg", "https://s3-media1.fl.yelpcdn.com/bphoto/CjfkJuz4MUJv9MPmsymicA/o.jpg", "https://s3-media4.fl.yelpcdn.com/bphoto/3LKZ--g3o688v_h4h2LpjA/o.jpg"]}