{"time_created": "2017-02-24 22:44:37", "user": {"image_url": "https://s3-media4.fl.yelpcdn.com/photo/ksvExelBmzEfTdU5OdvMyQ/o.jpg", "name": "Anna F."}, "rating": 4, "restaurant_id": "coast-bar-and-kitchen-austin", "url": "https://www.yelp.com/biz/coast-bar-and-kitchen-austin?hrid=WAusqwnmkp5BNTukBNnsNw&adjust_creative=92p07_JjKyriZTQxAXRiKQ&utm_campaign=yelp_api_v3&utm_medium=api_v3_business_reviews&utm_source=92p07_JjKyriZTQxAXRiKQ", "text": "Very small inside - make a reservation! Outside patio is open seating. \n\nKind of pricey drinks and food for what you get. Even apps are ~$15+.\n\nPrawns with..."}